dj_hybrid/__init__.py
dj_hybrid/decorator.py
dj_hybrid/expander.py
dj_hybrid/resolve.py
dj_hybrid/types.py
dj_hybrid/utils.py
dj_hybrid/expression_wrapper/__init__.py
dj_hybrid/expression_wrapper/base.py
dj_hybrid/expression_wrapper/registry.py
dj_hybrid/expression_wrapper/types.py
dj_hybrid/expression_wrapper/wrap.py
dj_hybrid/expression_wrapper/wrappers.py
dj_hybrid/tests/__init__.py
dj_hybrid/tests/settings.py
dj_hybrid/tests/test_control_flow.py
dj_hybrid/tests/test_decorator.py
dj_hybrid/tests/test_expander.py
dj_hybrid/tests/test_expression_wrapper.py
dj_hybrid/tests/test_self.py
dj_hybrid/tests/utils.py
dj_hybrid/tests/expression_wrapper/__init__.py
dj_hybrid/tests/expression_wrapper/test_registry.py
dj_hybrid/tests/expression_wrapper/test_wrap.py
dj_hybrid/tests/expression_wrapper/wrapper/__init__.py
dj_hybrid/tests/expression_wrapper/wrapper/base.py
dj_hybrid/tests/expression_wrapper/wrapper/factory.py
dj_hybrid/tests/expression_wrapper/wrapper/models.py
dj_hybrid/tests/expression_wrapper/wrapper/test_f.py
dj_hybrid/tests/expression_wrapper/wrapper/test_value.py
django_hybrid-0.2.0a2.dist-info/LICENSE.txt
django_hybrid-0.2.0a2.dist-info/METADATA
django_hybrid-0.2.0a2.dist-info/RECORD
django_hybrid-0.2.0a2.dist-info/WHEEL
django_hybrid-0.2.0a2.dist-info/top_level.txt
django_hybrid-0.2.0a2.dist-info/zip-safe
